{
  "klass": "Specie",
  "id": 181,
  "dbSymbol": "ampharos",
  "forms": [
    {
      "form": 0,
      "height": 1.4,
      "weight": 61.5,
      "type1": "electric",
      "type2": "__undef__",
      "baseHp": 90,
      "baseAtk": 75,
      "baseDfe": 75,
      "baseSpd": 55,
      "baseAts": 115,
      "baseDfs": 90,
      "evHp": 0,
      "evAtk": 0,
      "evDfe": 0,
      "evSpd": 0,
      "evAts": 3,
      "evDfs": 0,
      "evolutions": [],
      "experienceType": 3,
      "baseExperience": 196,
      "baseLoyalty": 70,
      "catchRate": 45,
      "femaleRate": 50,
      "breedGroups": [
        1,
        5
      ],
      "hatchSteps": 5120,
      "babyDbSymbol": "mareep",
      "babyForm": 0,
      "itemHeld": [],
      "abilities": [
        "static",
        "static",
        "plus"
      ],
      "frontOffsetY": 0,
      "moveSet": [
        {
          "klass": "LevelLearnableMove",
          "move": "tackle",
          "level": 1
        },
        {
          "klass": "LevelLearnableMove",
          "move": "growl",
          "level": 1
        },
        {
          "klass": "LevelLearnableMove",
          "move": "thunder_shock",
          "level": 1
        },
        {
          "klass": "LevelLearnableMove",
          "move": "thunder_wave",
          "level": 1
        },
        {
          "klass": "LevelLearnableMove",
          "move": "thunder_shock",
          "level": 9
        },
        {
          "klass": "LevelLearnableMove",
          "move": "thunder_wave",
          "level": 18
        },
        {
          "klass": "LevelLearnableMove",
          "move": "cotton_spore",
          "level": 27
        },
        {
          "klass": "LevelLearnableMove",
          "move": "thunder_punch",
          "level": 30
        },
        {
          "klass": "LevelLearnableMove",
          "move": "light_screen",
          "level": 42
        },
        {
          "klass": "LevelLearnableMove",
          "move": "thunder",
          "level": 57
        },
        {
          "klass": "TutorLearnableMove",
          "move": "sleep_talk"
        },
        {
          "klass": "TutorLearnableMove",
          "move": "defense_curl"
        },
        {
          "klass": "TutorLearnableMove",
          "move": "thunder_wave"
        },
        {
          "klass": "TutorLearnableMove",
          "move": "substitute"
        },
        {
          "klass": "TutorLearnableMove",
          "move": "mimic"
        },
        {
          "klass": "TutorLearnableMove",
          "move": "double_edge"
        },
        {
          "klass": "TutorLearnableMove",
          "move": "dynamic_punch"
        },
        {
          "klass": "TutorLearnableMove",
          "move": "seismic_toss"
        },
        {
          "klass": "TutorLearnableMove",
          "move": "swift"
        },
        {
          "klass": "TutorLearnableMove",
          "move": "body_slam"
        },
        {
          "klass": "TutorLearnableMove",
          "move": "thunder_punch"
        },
        {
          "klass": "TutorLearnableMove",
          "move": "fire_punch"
        },
        {
          "klass": "TutorLearnableMove",
          "move": "counter"
        },
        {
          "klass": "TutorLearnableMove",
          "move": "snore"
        },
        {
          "klass": "TutorLearnableMove",
          "move": "endure"
        },
        {
          "klass": "TutorLearnableMove",
          "move": "mega_kick"
        },
        {
          "klass": "TutorLearnableMove",
          "move": "mega_punch"
        },
        {
          "klass": "TutorLearnableMove",
          "move": "swagger"
        },
        {
          "klass": "TechLearnableMove",
          "move": "hyper_beam"
        },
        {
          "klass": "TechLearnableMove",
          "move": "strength"
        },
        {
          "klass": "TechLearnableMove",
          "move": "flash"
        },
        {
          "klass": "TechLearnableMove",
          "move": "rock_smash"
        },
        {
          "klass": "TechLearnableMove",
          "move": "focus_punch"
        },
        {
          "klass": "TechLearnableMove",
          "move": "toxic"
        },
        {
          "klass": "TechLearnableMove",
          "move": "hidden_power"
        },
        {
          "klass": "TechLearnableMove",
          "move": "light_screen"
        },
        {
          "klass": "TechLearnableMove",
          "move": "protect"
        },
        {
          "klass": "TechLearnableMove",
          "move": "rain_dance"
        },
        {
          "klass": "TechLearnableMove",
          "move": "frustration"
        },
        {
          "klass": "TechLearnableMove",
          "move": "iron_tail"
        },
        {
          "klass": "TechLearnableMove",
          "move": "thunderbolt"
        },
        {
          "klass": "TechLearnableMove",
          "move": "thunder"
        },
        {
          "klass": "TechLearnableMove",
          "move": "return"
        },
        {
          "klass": "TechLearnableMove",
          "move": "brick_break"
        },
        {
          "klass": "TechLearnableMove",
          "move": "double_team"
        },
        {
          "klass": "TechLearnableMove",
          "move": "shock_wave"
        },
        {
          "klass": "TechLearnableMove",
          "move": "facade"
        },
        {
          "klass": "TechLearnableMove",
          "move": "secret_power"
        },
        {
          "klass": "TechLearnableMove",
          "move": "rest"
        },
        {
          "klass": "TechLearnableMove",
          "move": "attract"
        }
      ],
      "resources": {
        "icon": "181",
        "iconShiny": "",
        "front": "181",
        "frontShiny": "181",
        "back": "181",
        "backShiny": "181",
        "footprint": "181",
        "character": "181_0",
        "characterShiny": "181s_0",
        "cry": "181cry.ogg",
        "hasFemale": false
      }
    }
  ]
}