{
  "klass": "Specie",
  "id": 57,
  "dbSymbol": "primeape",
  "forms": [
    {
      "form": 0,
      "formTextId": {
        "name": 63,
        "description": 0
      },
      "height": 1,
      "weight": 32,
      "type1": "fighting",
      "type2": "__undef__",
      "baseHp": 65,
      "baseAtk": 105,
      "baseDfe": 60,
      "baseSpd": 95,
      "baseAts": 60,
      "baseDfs": 70,
      "evHp": 0,
      "evAtk": 2,
      "evDfe": 0,
      "evSpd": 0,
      "evAts": 0,
      "evDfs": 0,
      "evolutions": [],
      "experienceType": 1,
      "baseExperience": 159,
      "baseLoyalty": 70,
      "catchRate": 75,
      "femaleRate": 50,
      "breedGroups": [
        5,
        5
      ],
      "hatchSteps": 5120,
      "babyDbSymbol": "mankey",
      "babyForm": 0,
      "itemHeld": [
        {
          "dbSymbol": "none",
          "chance": 0
        },
        {
          "dbSymbol": "none",
          "chance": 0
        }
      ],
      "abilities": [
        "vital_spirit",
        "vital_spirit",
        "vital_spirit"
      ],
      "frontOffsetY": 0,
      "resources": {
        "icon": "0057",
        "iconShiny": "0057s",
        "front": "0057",
        "frontShiny": "0057s",
        "back": "0057",
        "backShiny": "0057s",
        "footprint": "0057",
        "character": "0057",
        "characterShiny": "0057s",
        "cry": "0057.ogg",
        "hasFemale": false
      },
      "moveSet": [
        {
          "move": "scratch",
          "klass": "LevelLearnableMove",
          "level": 1
        },
        {
          "move": "leer",
          "klass": "LevelLearnableMove",
          "level": 1
        },
        {
          "move": "low_kick",
          "klass": "LevelLearnableMove",
          "level": 1
        },
        {
          "move": "rage",
          "klass": "LevelLearnableMove",
          "level": 1
        },
        {
          "move": "low_kick",
          "klass": "LevelLearnableMove",
          "level": 6
        },
        {
          "move": "karate_chop",
          "klass": "LevelLearnableMove",
          "level": 11
        },
        {
          "move": "fury_swipes",
          "klass": "LevelLearnableMove",
          "level": 16
        },
        {
          "move": "focus_energy",
          "klass": "LevelLearnableMove",
          "level": 21
        },
        {
          "move": "seismic_toss",
          "klass": "LevelLearnableMove",
          "level": 26
        },
        {
          "move": "rage",
          "klass": "LevelLearnableMove",
          "level": 28
        },
        {
          "move": "cross_chop",
          "klass": "LevelLearnableMove",
          "level": 35
        },
        {
          "move": "swagger",
          "klass": "LevelLearnableMove",
          "level": 44
        },
        {
          "move": "screech",
          "klass": "LevelLearnableMove",
          "level": 53
        },
        {
          "move": "thrash",
          "klass": "LevelLearnableMove",
          "level": 62
        },
        {
          "move": "mega_punch",
          "klass": "TutorLearnableMove"
        },
        {
          "move": "mega_kick",
          "klass": "TutorLearnableMove"
        },
        {
          "move": "body_slam",
          "klass": "TutorLearnableMove"
        },
        {
          "move": "double_edge",
          "klass": "TutorLearnableMove"
        },
        {
          "move": "hyper_beam",
          "klass": "TechLearnableMove"
        },
        {
          "move": "counter",
          "klass": "TutorLearnableMove"
        },
        {
          "move": "seismic_toss",
          "klass": "TutorLearnableMove"
        },
        {
          "move": "strength",
          "klass": "TechLearnableMove"
        },
        {
          "move": "thunderbolt",
          "klass": "TechLearnableMove"
        },
        {
          "move": "thunder",
          "klass": "TechLearnableMove"
        },
        {
          "move": "earthquake",
          "klass": "TechLearnableMove"
        },
        {
          "move": "dig",
          "klass": "TechLearnableMove"
        },
        {
          "move": "toxic",
          "klass": "TechLearnableMove"
        },
        {
          "move": "mimic",
          "klass": "TutorLearnableMove"
        },
        {
          "move": "double_team",
          "klass": "TechLearnableMove"
        },
        {
          "move": "metronome",
          "klass": "TutorLearnableMove"
        },
        {
          "move": "rest",
          "klass": "TechLearnableMove"
        },
        {
          "move": "rock_slide",
          "klass": "TutorLearnableMove"
        },
        {
          "move": "substitute",
          "klass": "TutorLearnableMove"
        },
        {
          "move": "thief",
          "klass": "TechLearnableMove"
        },
        {
          "move": "protect",
          "klass": "TechLearnableMove"
        },
        {
          "move": "attract",
          "klass": "TechLearnableMove"
        },
        {
          "move": "return",
          "klass": "TechLearnableMove"
        },
        {
          "move": "frustration",
          "klass": "TechLearnableMove"
        },
        {
          "move": "iron_tail",
          "klass": "TechLearnableMove"
        },
        {
          "move": "hidden_power",
          "klass": "TechLearnableMove"
        },
        {
          "move": "rain_dance",
          "klass": "TechLearnableMove"
        },
        {
          "move": "sunny_day",
          "klass": "TechLearnableMove"
        },
        {
          "move": "rock_smash",
          "klass": "TechLearnableMove"
        },
        {
          "move": "facade",
          "klass": "TechLearnableMove"
        },
        {
          "move": "focus_punch",
          "klass": "TechLearnableMove"
        },
        {
          "move": "taunt",
          "klass": "TechLearnableMove"
        },
        {
          "move": "brick_break",
          "klass": "TechLearnableMove"
        },
        {
          "move": "secret_power",
          "klass": "TechLearnableMove"
        },
        {
          "move": "overheat",
          "klass": "TechLearnableMove"
        },
        {
          "move": "rock_tomb",
          "klass": "TechLearnableMove"
        },
        {
          "move": "aerial_ace",
          "klass": "TechLearnableMove"
        },
        {
          "move": "bulk_up",
          "klass": "TechLearnableMove"
        }
      ]
    }
  ]
}