{
  "klass": "Specie",
  "id": 142,
  "dbSymbol": "aerodactyl",
  "forms": [
    {
      "form": 0,
      "height": 1.8,
      "weight": 59,
      "type1": "rock",
      "type2": "flying",
      "baseHp": 80,
      "baseAtk": 105,
      "baseDfe": 65,
      "baseSpd": 130,
      "baseAts": 60,
      "baseDfs": 75,
      "evHp": 0,
      "evAtk": 0,
      "evDfe": 0,
      "evSpd": 2,
      "evAts": 0,
      "evDfs": 0,
      "evolutions": [],
      "experienceType": 2,
      "baseExperience": 202,
      "baseLoyalty": 70,
      "catchRate": 45,
      "femaleRate": 12,
      "breedGroups": [
        4,
        4
      ],
      "hatchSteps": 8960,
      "babyDbSymbol": "aerodactyl",
      "babyForm": 0,
      "itemHeld": [
        {
          "dbSymbol": "none",
          "chance": 0
        },
        {
          "dbSymbol": "none",
          "chance": 0
        }
      ],
      "abilities": [
        "pressure",
        "rock_head",
        "unnerve"
      ],
      "frontOffsetY": 0,
      "moveSet": [
        {
          "klass": "LevelLearnableMove",
          "move": "wing_attack",
          "level": 1
        },
        {
          "klass": "LevelLearnableMove",
          "move": "agility",
          "level": 8
        },
        {
          "klass": "LevelLearnableMove",
          "move": "bite",
          "level": 15
        },
        {
          "klass": "LevelLearnableMove",
          "move": "supersonic",
          "level": 22
        },
        {
          "klass": "LevelLearnableMove",
          "move": "ancient_power",
          "level": 29
        },
        {
          "klass": "LevelLearnableMove",
          "move": "scary_face",
          "level": 36
        },
        {
          "klass": "LevelLearnableMove",
          "move": "take_down",
          "level": 43
        },
        {
          "klass": "LevelLearnableMove",
          "move": "hyper_beam",
          "level": 50
        },
        {
          "klass": "TutorLearnableMove",
          "move": "flamethrower"
        },
        {
          "klass": "TechLearnableMove",
          "move": "steel_wing"
        },
        {
          "klass": "TechLearnableMove",
          "move": "fly"
        },
        {
          "klass": "TechLearnableMove",
          "move": "headbutt"
        },
        {
          "klass": "TechLearnableMove",
          "move": "curse"
        },
        {
          "klass": "TechLearnableMove",
          "move": "roar"
        },
        {
          "klass": "TechLearnableMove",
          "move": "toxic"
        },
        {
          "klass": "TechLearnableMove",
          "move": "rock_smash"
        },
        {
          "klass": "TechLearnableMove",
          "move": "hidden_power"
        },
        {
          "klass": "TechLearnableMove",
          "move": "snore"
        },
        {
          "klass": "TechLearnableMove",
          "move": "hyper_beam"
        },
        {
          "klass": "TechLearnableMove",
          "move": "protect"
        },
        {
          "klass": "TechLearnableMove",
          "move": "rain_dance"
        },
        {
          "klass": "TechLearnableMove",
          "move": "endure"
        },
        {
          "klass": "TechLearnableMove",
          "move": "frustration"
        },
        {
          "klass": "TechLearnableMove",
          "move": "iron_tail"
        },
        {
          "klass": "TechLearnableMove",
          "move": "dragon_breath"
        },
        {
          "klass": "TechLearnableMove",
          "move": "earthquake"
        },
        {
          "klass": "TechLearnableMove",
          "move": "return"
        },
        {
          "klass": "TechLearnableMove",
          "move": "double_team"
        },
        {
          "klass": "TechLearnableMove",
          "move": "swagger"
        },
        {
          "klass": "TechLearnableMove",
          "move": "sleep_talk"
        },
        {
          "klass": "TechLearnableMove",
          "move": "sandstorm"
        },
        {
          "klass": "TechLearnableMove",
          "move": "fire_blast"
        },
        {
          "klass": "TechLearnableMove",
          "move": "swift"
        },
        {
          "klass": "TechLearnableMove",
          "move": "detect"
        },
        {
          "klass": "TechLearnableMove",
          "move": "rest"
        },
        {
          "klass": "TechLearnableMove",
          "move": "attract"
        },
        {
          "klass": "BreedLearnableMove",
          "move": "foresight"
        },
        {
          "klass": "BreedLearnableMove",
          "move": "pursuit"
        },
        {
          "klass": "BreedLearnableMove",
          "move": "steel_wing"
        },
        {
          "klass": "BreedLearnableMove",
          "move": "whirlwind"
        }
      ],
      "resources": {
        "icon": "142",
        "iconShiny": "",
        "front": "142",
        "frontShiny": "142",
        "back": "142",
        "backShiny": "142",
        "footprint": "142",
        "character": "142_0",
        "characterShiny": "142s_0",
        "cry": "142cry.ogg",
        "hasFemale": false
      }
    }
  ]
}