{
  "klass": "Specie",
  "id": 76,
  "dbSymbol": "golem",
  "forms": [
    {
      "form": 0,
      "formTextId": {
        "name": 82,
        "description": 0
      },
      "height": 1.4,
      "weight": 300,
      "type1": "rock",
      "type2": "ground",
      "baseHp": 80,
      "baseAtk": 110,
      "baseDfe": 130,
      "baseSpd": 45,
      "baseAts": 55,
      "baseDfs": 65,
      "evHp": 0,
      "evAtk": 0,
      "evDfe": 3,
      "evSpd": 0,
      "evAts": 0,
      "evDfs": 0,
      "evolutions": [],
      "experienceType": 3,
      "baseExperience": 223,
      "baseLoyalty": 70,
      "catchRate": 45,
      "femaleRate": 50,
      "breedGroups": [
        10,
        10
      ],
      "hatchSteps": 3840,
      "babyDbSymbol": "geodude",
      "babyForm": 0,
      "itemHeld": [
        {
          "dbSymbol": "none",
          "chance": 0
        },
        {
          "dbSymbol": "none",
          "chance": 0
        }
      ],
      "abilities": [
        "sturdy",
        "rock_head",
        "sturdy"
      ],
      "frontOffsetY": 0,
      "resources": {
        "icon": "0076",
        "iconShiny": "0076s",
        "front": "0076",
        "frontShiny": "0076s",
        "back": "0076",
        "backShiny": "0076s",
        "footprint": "0076",
        "character": "0076",
        "characterShiny": "0076s",
        "cry": "0076.ogg",
        "hasFemale": false
      },
      "moveSet": [
        {
          "move": "tackle",
          "klass": "LevelLearnableMove",
          "level": 1
        },
        {
          "move": "rock_throw",
          "klass": "LevelLearnableMove",
          "level": 1
        },
        {
          "move": "defense_curl",
          "klass": "LevelLearnableMove",
          "level": 1
        },
        {
          "move": "magnitude",
          "klass": "LevelLearnableMove",
          "level": 1
        },
        {
          "move": "defense_curl",
          "klass": "LevelLearnableMove",
          "level": 6
        },
        {
          "move": "rock_throw",
          "klass": "LevelLearnableMove",
          "level": 11
        },
        {
          "move": "magnitude",
          "klass": "LevelLearnableMove",
          "level": 16
        },
        {
          "move": "self_destruct",
          "klass": "LevelLearnableMove",
          "level": 21
        },
        {
          "move": "harden",
          "klass": "LevelLearnableMove",
          "level": 27
        },
        {
          "move": "rollout",
          "klass": "LevelLearnableMove",
          "level": 34
        },
        {
          "move": "earthquake",
          "klass": "LevelLearnableMove",
          "level": 41
        },
        {
          "move": "explosion",
          "klass": "LevelLearnableMove",
          "level": 48
        },
        {
          "move": "fire_punch",
          "klass": "TechLearnableMove"
        },
        {
          "move": "headbutt",
          "klass": "TechLearnableMove"
        },
        {
          "move": "roar",
          "klass": "TechLearnableMove"
        },
        {
          "move": "hyper_beam",
          "klass": "TechLearnableMove"
        },
        {
          "move": "strength",
          "klass": "TechLearnableMove"
        },
        {
          "move": "earthquake",
          "klass": "TechLearnableMove"
        },
        {
          "move": "dig",
          "klass": "TechLearnableMove"
        },
        {
          "move": "toxic",
          "klass": "TechLearnableMove"
        },
        {
          "move": "double_team",
          "klass": "TechLearnableMove"
        },
        {
          "move": "defense_curl",
          "klass": "TechLearnableMove"
        },
        {
          "move": "fire_blast",
          "klass": "TechLearnableMove"
        },
        {
          "move": "rest",
          "klass": "TechLearnableMove"
        },
        {
          "move": "snore",
          "klass": "TechLearnableMove"
        },
        {
          "move": "curse",
          "klass": "TechLearnableMove"
        },
        {
          "move": "protect",
          "klass": "TechLearnableMove"
        },
        {
          "move": "mud_slap",
          "klass": "TechLearnableMove"
        },
        {
          "move": "sandstorm",
          "klass": "TechLearnableMove"
        },
        {
          "move": "endure",
          "klass": "TechLearnableMove"
        },
        {
          "move": "rollout",
          "klass": "TechLearnableMove"
        },
        {
          "move": "swagger",
          "klass": "TechLearnableMove"
        },
        {
          "move": "fury_cutter",
          "klass": "TechLearnableMove"
        },
        {
          "move": "attract",
          "klass": "TechLearnableMove"
        },
        {
          "move": "sleep_talk",
          "klass": "TechLearnableMove"
        },
        {
          "move": "return",
          "klass": "TechLearnableMove"
        },
        {
          "move": "frustration",
          "klass": "TechLearnableMove"
        },
        {
          "move": "dynamic_punch",
          "klass": "TechLearnableMove"
        },
        {
          "move": "hidden_power",
          "klass": "TechLearnableMove"
        },
        {
          "move": "sunny_day",
          "klass": "TechLearnableMove"
        },
        {
          "move": "rock_smash",
          "klass": "TechLearnableMove"
        }
      ]
    }
  ]
}