{
  "klass": "Specie",
  "id": 88,
  "dbSymbol": "grimer",
  "forms": [
    {
      "form": 0,
      "formTextId": {
        "name": 94,
        "description": 0
      },
      "height": 0.9,
      "weight": 30,
      "type1": "poison",
      "type2": "__undef__",
      "baseHp": 80,
      "baseAtk": 80,
      "baseDfe": 50,
      "baseSpd": 25,
      "baseAts": 40,
      "baseDfs": 50,
      "evHp": 1,
      "evAtk": 0,
      "evDfe": 0,
      "evSpd": 0,
      "evAts": 0,
      "evDfs": 0,
      "evolutions": [
        {
          "dbSymbol": "muk",
          "form": 0,
          "conditions": [
            {
              "type": "minLevel",
              "value": 38
            }
          ]
        }
      ],
      "experienceType": 1,
      "baseExperience": 65,
      "baseLoyalty": 70,
      "catchRate": 190,
      "femaleRate": 50,
      "breedGroups": [
        11,
        11
      ],
      "hatchSteps": 5140,
      "babyDbSymbol": "grimer",
      "babyForm": 0,
      "itemHeld": [
        {
          "dbSymbol": "none",
          "chance": 0
        },
        {
          "dbSymbol": "none",
          "chance": 0
        }
      ],
      "abilities": [
        "stench",
        "sticky_hold",
        "poison_touch"
      ],
      "frontOffsetY": 0,
      "resources": {
        "icon": "0088",
        "iconShiny": "0088s",
        "front": "0088",
        "frontShiny": "0088s",
        "back": "0088",
        "backShiny": "0088s",
        "footprint": "0088",
        "character": "0088",
        "characterShiny": "0088s",
        "cry": "0088.ogg",
        "hasFemale": false
      },
      "moveSet": [
        {
          "move": "pound",
          "klass": "LevelLearnableMove",
          "level": 1
        },
        {
          "move": "poison_gas",
          "klass": "LevelLearnableMove",
          "level": 1
        },
        {
          "move": "harden",
          "klass": "LevelLearnableMove",
          "level": 4
        },
        {
          "move": "mud_slap",
          "klass": "LevelLearnableMove",
          "level": 7
        },
        {
          "move": "disable",
          "klass": "LevelLearnableMove",
          "level": 12
        },
        {
          "move": "sludge",
          "klass": "LevelLearnableMove",
          "level": 15
        },
        {
          "move": "minimize",
          "klass": "LevelLearnableMove",
          "level": 18
        },
        {
          "move": "mud_bomb",
          "klass": "LevelLearnableMove",
          "level": 21
        },
        {
          "move": "sludge_bomb",
          "klass": "LevelLearnableMove",
          "level": 26
        },
        {
          "move": "fling",
          "klass": "LevelLearnableMove",
          "level": 29
        },
        {
          "move": "screech",
          "klass": "LevelLearnableMove",
          "level": 32
        },
        {
          "move": "sludge_wave",
          "klass": "LevelLearnableMove",
          "level": 37
        },
        {
          "move": "acid_armor",
          "klass": "LevelLearnableMove",
          "level": 40
        },
        {
          "move": "gunk_shot",
          "klass": "LevelLearnableMove",
          "level": 43
        },
        {
          "move": "memento",
          "klass": "LevelLearnableMove",
          "level": 48
        },
        {
          "move": "fire_punch",
          "klass": "TutorLearnableMove"
        },
        {
          "move": "ice_punch",
          "klass": "TutorLearnableMove"
        },
        {
          "move": "thunder_punch",
          "klass": "TutorLearnableMove"
        },
        {
          "move": "flamethrower",
          "klass": "TechLearnableMove"
        },
        {
          "move": "strength",
          "klass": "TechLearnableMove"
        },
        {
          "move": "thunderbolt",
          "klass": "TechLearnableMove"
        },
        {
          "move": "thunder",
          "klass": "TechLearnableMove"
        },
        {
          "move": "dig",
          "klass": "TechLearnableMove"
        },
        {
          "move": "toxic",
          "klass": "TechLearnableMove"
        },
        {
          "move": "double_team",
          "klass": "TechLearnableMove"
        },
        {
          "move": "haze",
          "klass": "BreedLearnableMove"
        },
        {
          "move": "lick",
          "klass": "BreedLearnableMove"
        },
        {
          "move": "fire_blast",
          "klass": "TechLearnableMove"
        },
        {
          "move": "explosion",
          "klass": "TechLearnableMove"
        },
        {
          "move": "rest",
          "klass": "TechLearnableMove"
        },
        {
          "move": "rock_slide",
          "klass": "TechLearnableMove"
        },
        {
          "move": "substitute",
          "klass": "TechLearnableMove"
        },
        {
          "move": "thief",
          "klass": "TechLearnableMove"
        },
        {
          "move": "snore",
          "klass": "TutorLearnableMove"
        },
        {
          "move": "curse",
          "klass": "BreedLearnableMove"
        },
        {
          "move": "protect",
          "klass": "TechLearnableMove"
        },
        {
          "move": "scary_face",
          "klass": "BreedLearnableMove"
        },
        {
          "move": "sludge_bomb",
          "klass": "TechLearnableMove"
        },
        {
          "move": "giga_drain",
          "klass": "TutorLearnableMove"
        },
        {
          "move": "swagger",
          "klass": "TechLearnableMove"
        },
        {
          "move": "mean_look",
          "klass": "BreedLearnableMove"
        },
        {
          "move": "attract",
          "klass": "TechLearnableMove"
        },
        {
          "move": "sleep_talk",
          "klass": "TutorLearnableMove"
        },
        {
          "move": "return",
          "klass": "TechLearnableMove"
        },
        {
          "move": "frustration",
          "klass": "TechLearnableMove"
        },
        {
          "move": "pain_split",
          "klass": "TutorLearnableMove"
        },
        {
          "move": "hidden_power",
          "klass": "TechLearnableMove"
        },
        {
          "move": "rain_dance",
          "klass": "TechLearnableMove"
        },
        {
          "move": "sunny_day",
          "klass": "TechLearnableMove"
        },
        {
          "move": "shadow_ball",
          "klass": "TechLearnableMove"
        },
        {
          "move": "stockpile",
          "klass": "BreedLearnableMove"
        },
        {
          "move": "spit_up",
          "klass": "BreedLearnableMove"
        },
        {
          "move": "swallow",
          "klass": "BreedLearnableMove"
        },
        {
          "move": "torment",
          "klass": "TechLearnableMove"
        },
        {
          "move": "facade",
          "klass": "TechLearnableMove"
        },
        {
          "move": "taunt",
          "klass": "TechLearnableMove"
        },
        {
          "move": "imprison",
          "klass": "BreedLearnableMove"
        },
        {
          "move": "rock_tomb",
          "klass": "TechLearnableMove"
        },
        {
          "move": "shadow_punch",
          "klass": "BreedLearnableMove"
        },
        {
          "move": "payback",
          "klass": "TechLearnableMove"
        },
        {
          "move": "fling",
          "klass": "TechLearnableMove"
        },
        {
          "move": "poison_jab",
          "klass": "TechLearnableMove"
        },
        {
          "move": "shadow_sneak",
          "klass": "BreedLearnableMove"
        },
        {
          "move": "gunk_shot",
          "klass": "TutorLearnableMove"
        },
        {
          "move": "venoshock",
          "klass": "TechLearnableMove"
        },
        {
          "move": "sludge_wave",
          "klass": "TechLearnableMove"
        },
        {
          "move": "acid_spray",
          "klass": "BreedLearnableMove"
        },
        {
          "move": "round",
          "klass": "TechLearnableMove"
        },
        {
          "move": "incinerate",
          "klass": "TechLearnableMove"
        }
      ]
    }
  ]
}