{
  "klass": "Specie",
  "id": 820,
  "dbSymbol": "greedent",
  "forms": [
    {
      "form": 0,
      "height": 0.6,
      "weight": 6,
      "type1": "normal",
      "type2": "__undef__",
      "baseHp": 120,
      "baseAtk": 95,
      "baseDfe": 95,
      "baseSpd": 20,
      "baseAts": 55,
      "baseDfs": 75,
      "evHp": 2,
      "evAtk": 0,
      "evDfe": 0,
      "evSpd": 0,
      "evAts": 0,
      "evDfs": 0,
      "evolutions": [],
      "experienceType": 1,
      "baseExperience": 161,
      "baseLoyalty": 50,
      "catchRate": 90,
      "femaleRate": 50,
      "breedGroups": [
        5,
        5
      ],
      "hatchSteps": 5120,
      "babyDbSymbol": "skwovet",
      "babyForm": 0,
      "itemHeld": [
        {
          "dbSymbol": "none",
          "chance": 0
        },
        {
          "dbSymbol": "none",
          "chance": 0
        }
      ],
      "abilities": [
        "cheek_pouch",
        "cheek_pouch",
        "gluttony"
      ],
      "frontOffsetY": 0,
      "resources": {
        "icon": "820",
        "iconShiny": "",
        "front": "820",
        "frontShiny": "820",
        "back": "820",
        "backShiny": "820",
        "footprint": "",
        "character": "820_0",
        "characterShiny": "820s_0",
        "cry": "820cry.ogg",
        "hasFemale": false
      },
      "moveSet": [
        {
          "klass": "LevelLearnableMove",
          "move": "tackle",
          "level": 1
        },
        {
          "klass": "LevelLearnableMove",
          "move": "tail_whip",
          "level": 1
        },
        {
          "klass": "LevelLearnableMove",
          "move": "bite",
          "level": 1
        },
        {
          "klass": "LevelLearnableMove",
          "move": "stuff_cheeks",
          "level": 1
        },
        {
          "klass": "LevelLearnableMove",
          "move": "covet",
          "level": 1
        },
        {
          "klass": "LevelLearnableMove",
          "move": "stockpile",
          "level": 15
        },
        {
          "klass": "LevelLearnableMove",
          "move": "swallow",
          "level": 15
        },
        {
          "klass": "LevelLearnableMove",
          "move": "spit_up",
          "level": 15
        },
        {
          "klass": "LevelLearnableMove",
          "move": "body_slam",
          "level": 20
        },
        {
          "klass": "LevelLearnableMove",
          "move": "rest",
          "level": 27
        },
        {
          "klass": "LevelLearnableMove",
          "move": "counter",
          "level": 34
        },
        {
          "klass": "LevelLearnableMove",
          "move": "bullet_seed",
          "level": 41
        },
        {
          "klass": "LevelLearnableMove",
          "move": "super_fang",
          "level": 48
        },
        {
          "klass": "LevelLearnableMove",
          "move": "belch",
          "level": 55
        },
        {
          "klass": "BreedLearnableMove",
          "move": "belly_drum"
        },
        {
          "klass": "BreedLearnableMove",
          "move": "defense_curl"
        },
        {
          "klass": "BreedLearnableMove",
          "move": "last_resort"
        },
        {
          "klass": "BreedLearnableMove",
          "move": "rollout"
        },
        {
          "klass": "EvolutionLearnableMove",
          "move": "covet"
        },
        {
          "klass": "TechLearnableMove",
          "move": "dig"
        },
        {
          "klass": "TechLearnableMove",
          "move": "rest"
        },
        {
          "klass": "TechLearnableMove",
          "move": "thief"
        },
        {
          "klass": "TechLearnableMove",
          "move": "snore"
        },
        {
          "klass": "TechLearnableMove",
          "move": "protect"
        },
        {
          "klass": "TechLearnableMove",
          "move": "attract"
        },
        {
          "klass": "TechLearnableMove",
          "move": "facade"
        },
        {
          "klass": "TechLearnableMove",
          "move": "bullet_seed"
        },
        {
          "klass": "TechLearnableMove",
          "move": "mud_shot"
        },
        {
          "klass": "TechLearnableMove",
          "move": "payback"
        },
        {
          "klass": "TechLearnableMove",
          "move": "assurance"
        },
        {
          "klass": "TechLearnableMove",
          "move": "fling"
        },
        {
          "klass": "TechLearnableMove",
          "move": "round"
        },
        {
          "klass": "TechLearnableMove",
          "move": "tail_slap"
        },
        {
          "klass": "TechLearnableMove",
          "move": "brutal_swing"
        },
        {
          "klass": "TechLearnableMove",
          "move": "body_slam"
        },
        {
          "klass": "TechLearnableMove",
          "move": "amnesia"
        },
        {
          "klass": "TechLearnableMove",
          "move": "substitute"
        },
        {
          "klass": "TechLearnableMove",
          "move": "endure"
        },
        {
          "klass": "TechLearnableMove",
          "move": "sleep_talk"
        },
        {
          "klass": "TechLearnableMove",
          "move": "iron_tail"
        },
        {
          "klass": "TechLearnableMove",
          "move": "crunch"
        },
        {
          "klass": "TechLearnableMove",
          "move": "uproar"
        },
        {
          "klass": "TechLearnableMove",
          "move": "hyper_voice"
        },
        {
          "klass": "TechLearnableMove",
          "move": "gyro_ball"
        },
        {
          "klass": "TechLearnableMove",
          "move": "seed_bomb"
        },
        {
          "klass": "TechLearnableMove",
          "move": "hyper_beam"
        },
        {
          "klass": "TechLearnableMove",
          "move": "giga_impact"
        },
        {
          "klass": "TechLearnableMove",
          "move": "earthquake"
        },
        {
          "klass": "TechLearnableMove",
          "move": "wild_charge"
        },
        {
          "klass": "TechLearnableMove",
          "move": "psychic_fangs"
        },
        {
          "klass": "TechLearnableMove",
          "move": "body_press"
        },
        {
          "klass": "TechLearnableMove",
          "move": "swords_dance"
        },
        {
          "klass": "TechLearnableMove",
          "move": "superpower"
        },
        {
          "klass": "TechLearnableMove",
          "move": "stomping_tantrum"
        },
        {
          "klass": "TechLearnableMove",
          "move": "thunder_fang"
        },
        {
          "klass": "TechLearnableMove",
          "move": "ice_fang"
        },
        {
          "klass": "TechLearnableMove",
          "move": "fire_fang"
        }
      ],
      "formTextId": {
        "name": 1217,
        "description": 0
      }
    }
  ]
}