{
  "klass": "Specie",
  "id": 296,
  "dbSymbol": "makuhita",
  "forms": [
    {
      "form": 0,
      "height": 1,
      "weight": 86.4,
      "type1": "fighting",
      "type2": "__undef__",
      "baseHp": 72,
      "baseAtk": 60,
      "baseDfe": 30,
      "baseSpd": 25,
      "baseAts": 20,
      "baseDfs": 30,
      "evHp": 1,
      "evAtk": 0,
      "evDfe": 0,
      "evSpd": 0,
      "evAts": 0,
      "evDfs": 0,
      "evolutions": [
        {
          "dbSymbol": "hariyama",
          "form": 0,
          "conditions": [
            {
              "type": "minLevel",
              "value": 24
            }
          ]
        }
      ],
      "experienceType": 5,
      "baseExperience": 47,
      "baseLoyalty": 70,
      "catchRate": 180,
      "femaleRate": 25,
      "breedGroups": [
        8,
        8
      ],
      "hatchSteps": 5120,
      "babyDbSymbol": "makuhita",
      "babyForm": 0,
      "itemHeld": [
        {
          "dbSymbol": "none",
          "chance": 0
        },
        {
          "dbSymbol": "none",
          "chance": 0
        }
      ],
      "abilities": [
        "thick_fat",
        "guts",
        "thick_fat"
      ],
      "frontOffsetY": 0,
      "resources": {
        "icon": "0296",
        "iconShiny": "0296s",
        "front": "0296",
        "frontShiny": "0296s",
        "back": "0296",
        "backShiny": "0296s",
        "footprint": "0296",
        "character": "0296",
        "characterShiny": "0296s",
        "cry": "0296.ogg",
        "hasFemale": false
      },
      "moveSet": [
        {
          "move": "tackle",
          "klass": "LevelLearnableMove",
          "level": 1
        },
        {
          "move": "focus_energy",
          "klass": "LevelLearnableMove",
          "level": 1
        },
        {
          "move": "sand_attack",
          "klass": "LevelLearnableMove",
          "level": 4
        },
        {
          "move": "arm_thrust",
          "klass": "LevelLearnableMove",
          "level": 10
        },
        {
          "move": "vital_throw",
          "klass": "LevelLearnableMove",
          "level": 13
        },
        {
          "move": "fake_out",
          "klass": "LevelLearnableMove",
          "level": 19
        },
        {
          "move": "whirlwind",
          "klass": "LevelLearnableMove",
          "level": 22
        },
        {
          "move": "knock_off",
          "klass": "LevelLearnableMove",
          "level": 28
        },
        {
          "move": "smelling_salts",
          "klass": "LevelLearnableMove",
          "level": 31
        },
        {
          "move": "belly_drum",
          "klass": "LevelLearnableMove",
          "level": 37
        },
        {
          "move": "endure",
          "klass": "LevelLearnableMove",
          "level": 40
        },
        {
          "move": "seismic_toss",
          "klass": "LevelLearnableMove",
          "level": 46
        },
        {
          "move": "reversal",
          "klass": "LevelLearnableMove",
          "level": 49
        },
        {
          "move": "mega_punch",
          "klass": "TutorLearnableMove"
        },
        {
          "move": "fire_punch",
          "klass": "TutorLearnableMove"
        },
        {
          "move": "ice_punch",
          "klass": "TutorLearnableMove"
        },
        {
          "move": "thunder_punch",
          "klass": "TutorLearnableMove"
        },
        {
          "move": "mega_kick",
          "klass": "TutorLearnableMove"
        },
        {
          "move": "body_slam",
          "klass": "TutorLearnableMove"
        },
        {
          "move": "double_edge",
          "klass": "TutorLearnableMove"
        },
        {
          "move": "surf",
          "klass": "TechLearnableMove"
        },
        {
          "move": "counter",
          "klass": "BreedLearnableMove"
        },
        {
          "move": "counter",
          "klass": "TutorLearnableMove"
        },
        {
          "move": "seismic_toss",
          "klass": "TutorLearnableMove"
        },
        {
          "move": "strength",
          "klass": "TechLearnableMove"
        },
        {
          "move": "earthquake",
          "klass": "TechLearnableMove"
        },
        {
          "move": "dig",
          "klass": "TechLearnableMove"
        },
        {
          "move": "toxic",
          "klass": "TechLearnableMove"
        },
        {
          "move": "mimic",
          "klass": "TutorLearnableMove"
        },
        {
          "move": "double_team",
          "klass": "TechLearnableMove"
        },
        {
          "move": "metronome",
          "klass": "TutorLearnableMove"
        },
        {
          "move": "rest",
          "klass": "TechLearnableMove"
        },
        {
          "move": "rock_slide",
          "klass": "TutorLearnableMove"
        },
        {
          "move": "substitute",
          "klass": "TutorLearnableMove"
        },
        {
          "move": "snore",
          "klass": "TutorLearnableMove"
        },
        {
          "move": "protect",
          "klass": "TechLearnableMove"
        },
        {
          "move": "feint_attack",
          "klass": "BreedLearnableMove"
        },
        {
          "move": "mud_slap",
          "klass": "TutorLearnableMove"
        },
        {
          "move": "foresight",
          "klass": "BreedLearnableMove"
        },
        {
          "move": "detect",
          "klass": "BreedLearnableMove"
        },
        {
          "move": "endure",
          "klass": "TutorLearnableMove"
        },
        {
          "move": "swagger",
          "klass": "TutorLearnableMove"
        },
        {
          "move": "attract",
          "klass": "TechLearnableMove"
        },
        {
          "move": "sleep_talk",
          "klass": "TutorLearnableMove"
        },
        {
          "move": "return",
          "klass": "TechLearnableMove"
        },
        {
          "move": "frustration",
          "klass": "TechLearnableMove"
        },
        {
          "move": "dynamic_punch",
          "klass": "BreedLearnableMove"
        },
        {
          "move": "dynamic_punch",
          "klass": "TutorLearnableMove"
        },
        {
          "move": "hidden_power",
          "klass": "TechLearnableMove"
        },
        {
          "move": "cross_chop",
          "klass": "BreedLearnableMove"
        },
        {
          "move": "rain_dance",
          "klass": "TechLearnableMove"
        },
        {
          "move": "sunny_day",
          "klass": "TechLearnableMove"
        },
        {
          "move": "rock_smash",
          "klass": "TechLearnableMove"
        },
        {
          "move": "facade",
          "klass": "TechLearnableMove"
        },
        {
          "move": "focus_punch",
          "klass": "TechLearnableMove"
        },
        {
          "move": "helping_hand",
          "klass": "BreedLearnableMove"
        },
        {
          "move": "revenge",
          "klass": "BreedLearnableMove"
        },
        {
          "move": "brick_break",
          "klass": "TechLearnableMove"
        },
        {
          "move": "secret_power",
          "klass": "TechLearnableMove"
        },
        {
          "move": "rock_tomb",
          "klass": "TechLearnableMove"
        },
        {
          "move": "bulk_up",
          "klass": "TechLearnableMove"
        }
      ],
      "formTextId": {
        "name": 329,
        "description": 0
      }
    }
  ]
}