{
  "klass": "Specie",
  "id": 1,
  "dbSymbol": "bulbasaur",
  "forms": [
    {
      "form": 0,
      "height": 0.7,
      "weight": 6.9,
      "type1": "grass",
      "type2": "poison",
      "baseHp": 45,
      "baseAtk": 49,
      "baseDfe": 49,
      "baseSpd": 45,
      "baseAts": 65,
      "baseDfs": 65,
      "evHp": 0,
      "evAtk": 0,
      "evDfe": 0,
      "evSpd": 0,
      "evAts": 1,
      "evDfs": 0,
      "evolutions": [
        {
          "dbSymbol": "ivysaur",
          "form": 0,
          "conditions": [
            {
              "type": "minLevel",
              "value": 16
            }
          ]
        }
      ],
      "experienceType": 3,
      "baseExperience": 64,
      "baseLoyalty": 70,
      "catchRate": 45,
      "femaleRate": 12.5,
      "breedGroups": [
        1,
        7
      ],
      "hatchSteps": 5120,
      "babyDbSymbol": "bulbasaur",
      "babyForm": 0,
      "itemHeld": [
        {
          "dbSymbol": "none",
          "chance": 0
        },
        {
          "dbSymbol": "none",
          "chance": 0
        }
      ],
      "abilities": [
        "overgrow",
        "overgrow",
        "overgrow"
      ],
      "frontOffsetY": 0,
      "resources": {
        "icon": "0001",
        "iconShiny": "0001s",
        "front": "0001",
        "frontShiny": "0001s",
        "back": "0001",
        "backShiny": "0001s",
        "footprint": "0001",
        "character": "0001",
        "characterShiny": "0001s",
        "cry": "0001.ogg",
        "hasFemale": false
      },
      "moveSet": [
        {
          "move": "tackle",
          "klass": "LevelLearnableMove",
          "level": 1
        },
        {
          "move": "growl",
          "klass": "LevelLearnableMove",
          "level": 4
        },
        {
          "move": "leech_seed",
          "klass": "LevelLearnableMove",
          "level": 7
        },
        {
          "move": "vine_whip",
          "klass": "LevelLearnableMove",
          "level": 10
        },
        {
          "move": "poison_powder",
          "klass": "LevelLearnableMove",
          "level": 15
        },
        {
          "move": "sleep_powder",
          "klass": "LevelLearnableMove",
          "level": 15
        },
        {
          "move": "razor_leaf",
          "klass": "LevelLearnableMove",
          "level": 20
        },
        {
          "move": "sweet_scent",
          "klass": "LevelLearnableMove",
          "level": 25
        },
        {
          "move": "growth",
          "klass": "LevelLearnableMove",
          "level": 32
        },
        {
          "move": "synthesis",
          "klass": "LevelLearnableMove",
          "level": 39
        },
        {
          "move": "solar_beam",
          "klass": "LevelLearnableMove",
          "level": 46
        },
        {
          "move": "razor_wind",
          "klass": "BreedLearnableMove"
        },
        {
          "move": "cut",
          "klass": "TechLearnableMove"
        },
        {
          "move": "headbutt",
          "klass": "TechLearnableMove"
        },
        {
          "move": "solar_beam",
          "klass": "TechLearnableMove"
        },
        {
          "move": "petal_dance",
          "klass": "BreedLearnableMove"
        },
        {
          "move": "toxic",
          "klass": "TechLearnableMove"
        },
        {
          "move": "double_team",
          "klass": "TechLearnableMove"
        },
        {
          "move": "defense_curl",
          "klass": "TechLearnableMove"
        },
        {
          "move": "light_screen",
          "klass": "BreedLearnableMove"
        },
        {
          "move": "skull_bash",
          "klass": "BreedLearnableMove"
        },
        {
          "move": "flash",
          "klass": "TechLearnableMove"
        },
        {
          "move": "rest",
          "klass": "TechLearnableMove"
        },
        {
          "move": "snore",
          "klass": "TechLearnableMove"
        },
        {
          "move": "curse",
          "klass": "TechLearnableMove"
        },
        {
          "move": "protect",
          "klass": "TechLearnableMove"
        },
        {
          "move": "mud_slap",
          "klass": "TechLearnableMove"
        },
        {
          "move": "giga_drain",
          "klass": "TechLearnableMove"
        },
        {
          "move": "endure",
          "klass": "TechLearnableMove"
        },
        {
          "move": "swagger",
          "klass": "TechLearnableMove"
        },
        {
          "move": "fury_cutter",
          "klass": "TechLearnableMove"
        },
        {
          "move": "attract",
          "klass": "TechLearnableMove"
        },
        {
          "move": "sleep_talk",
          "klass": "TechLearnableMove"
        },
        {
          "move": "return",
          "klass": "TechLearnableMove"
        },
        {
          "move": "frustration",
          "klass": "TechLearnableMove"
        },
        {
          "move": "safeguard",
          "klass": "BreedLearnableMove"
        },
        {
          "move": "sweet_scent",
          "klass": "TechLearnableMove"
        },
        {
          "move": "hidden_power",
          "klass": "TechLearnableMove"
        },
        {
          "move": "sunny_day",
          "klass": "TechLearnableMove"
        }
      ],
      "formTextId": {
        "name": 0,
        "description": 0
      }
    }
  ]
}